LICENSE
MANIFEST.in
README.md
setup.cfg
setup.py
aa_miningtaxes.egg-info/PKG-INFO
aa_miningtaxes.egg-info/SOURCES.txt
aa_miningtaxes.egg-info/dependency_links.txt
aa_miningtaxes.egg-info/requires.txt
aa_miningtaxes.egg-info/top_level.txt
miningtaxes/__init__.py
miningtaxes/admin.py
miningtaxes/app_settings.py
miningtaxes/apps.py
miningtaxes/auth_hooks.py
miningtaxes/decorators.py
miningtaxes/forms.py
miningtaxes/helpers.py
miningtaxes/providers.py
miningtaxes/tasks.py
miningtaxes/urls.py
miningtaxes/views.py
miningtaxes/management/commands/__init__.py
miningtaxes/management/commands/miningtaxes_auto_add.py
miningtaxes/management/commands/miningtaxes_preload_prices.py
miningtaxes/management/commands/miningtaxes_prune_non_corpies.py
miningtaxes/management/commands/miningtaxes_update_debug.py
miningtaxes/management/commands/miningtaxes_update_manual.py
miningtaxes/management/commands/miningtaxes_zero_all.py
miningtaxes/migrations/0001_initial.py
miningtaxes/migrations/0002_all_models.py
miningtaxes/migrations/0003_alter_general_options.py
miningtaxes/migrations/0004_settings_interest_rate_alter_settings_phrase.py
miningtaxes/migrations/0005_oreprices_raw_price_oreprices_refined_price_and_more.py
miningtaxes/migrations/0006_charactertaxcredits_credit_type.py
miningtaxes/migrations/0007_character_life_credits_character_life_taxes.py
miningtaxes/migrations/0008_character_monthly_credits_json_and_more.py
miningtaxes/migrations/0009_stats.py
miningtaxes/migrations/0010_stats_admin_get_all_activity_json.py
miningtaxes/migrations/0011_stats_curmonth_leadergraph.py
miningtaxes/migrations/0012_stats_user_mining_ledger_90day.py
miningtaxes/migrations/0013_refactor_tax_rates.py
miningtaxes/migrations/__init__.py
miningtaxes/models/__init__.py
miningtaxes/models/admin.py
miningtaxes/models/character.py
miningtaxes/models/general.py
miningtaxes/models/orePrices.py
miningtaxes/models/settings.py
miningtaxes/models/stats.py
miningtaxes/static/miningtaxes/css/billboards_dark.css
miningtaxes/static/miningtaxes/css/billboards_light.css
miningtaxes/static/miningtaxes/css/global.css
miningtaxes/static/miningtaxes/css/launcher.css
