Metadata-Version: 2.1
Name: aa-miningtaxes
Version: 1.4.32
Summary: An Alliance Auth app that tracks and applies taxes for mining
Home-page: https://gitlab.com/arctiru/aa-miningtaxes
Author: Arc Tiru
Author-email: arcturusstl@gmail.com
License: MIT
Classifier: Environment :: Web Environment
Classifier: Framework :: Django
Classifier: Framework :: Django :: 3.2
Classifier: Intended Audience :: Developers
Classifier: License :: OSI Approved :: MIT License
Classifier: Operating System :: OS Independent
Classifier: Programming Language :: Python
Classifier: Programming Language :: Python :: 3.7
Classifier: Programming Language :: Python :: 3.8
Classifier: Programming Language :: Python :: 3.9
Classifier: Topic :: Internet :: WWW/HTTP
Classifier: Topic :: Internet :: WWW/HTTP :: Dynamic Content
Requires-Python: ~=3.7
License-File: LICENSE
